codal_tsetmc/__init__.py
codal_tsetmc/config/__init__.py
codal_tsetmc/config/config.default.yml
codal_tsetmc/config/engine.py
codal_tsetmc/download/__init__.py
codal_tsetmc/download/codal/__init__.py
codal_tsetmc/download/codal/category.py
codal_tsetmc/download/codal/company.py
codal_tsetmc/download/codal/letters.py
codal_tsetmc/download/codal/query.py
codal_tsetmc/download/tsetmc/__init__.py
codal_tsetmc/download/tsetmc/capital.py
codal_tsetmc/download/tsetmc/price.py
codal_tsetmc/download/tsetmc/stock.py
codal_tsetmc/initializer.py
codal_tsetmc/models/__init__.py
codal_tsetmc/models/codal/__init__.py
codal_tsetmc/models/codal/auditor.py
codal_tsetmc/models/codal/company.py
codal_tsetmc/models/codal/company_nature.py
codal_tsetmc/models/codal/company_state.py
codal_tsetmc/models/codal/company_type.py
codal_tsetmc/models/codal/financial_year.py
codal_tsetmc/models/codal/industry_group.py
codal_tsetmc/models/codal/letter.py
codal_tsetmc/models/codal/letter_group.py
codal_tsetmc/models/codal/letter_type.py
codal_tsetmc/models/create.py
codal_tsetmc/models/tsetmc/__init__.py
codal_tsetmc/models/tsetmc/stock.py
codal_tsetmc/models/tsetmc/stock_capital.py
codal_tsetmc/models/tsetmc/stock_group.py
codal_tsetmc/models/tsetmc/stock_price.py
codal_tsetmc/tools/__init__.py
codal_tsetmc/tools/api.py
codal_tsetmc/tools/database.py
codal_tsetmc/tools/exception.py
codal_tsetmc/tools/string.py
codal_tsetmc-3.1.1.dist-info/METADATA
codal_tsetmc-3.1.1.dist-info/WHEEL
codal_tsetmc-3.1.1.dist-info/licenses/LICENSE
codal_tsetmc-3.1.1.dist-info/RECORD
